[
  {
    "path": "group/schedule",
    "method": "GET",
    "statusCode": 200,
    "data": {
      "status": "ok",
      "response": {
        "list": [
          {
            "id": "0",
            "subject_name": "ПОТНЫЕ ЯЙЦА",
            "homework": "МУЖСКИЕ ПОТНЫЕ ЯЙЦА",
            "start": "2024-02-10 09:30:00.000",
            "end": "2024-02-10 10:30:00.000",
            "type": "seminar",
            "index": 1,
            "color": "yellow"

          },
          {
            "id": "1",
            "subject_name": "Матан",
            "homework": "Сделать задания 1-5, принести тетрадь с контрольным расчётом",
            "start": "2024-04-30 09:30:00.000",
            "end": "2024-04-30 10:30:00.000",
            "type": "seminar",
            "index": 1,
            "color": "yellow"

          },
          {
            "id": "2",
            "subject_name": "Машинка",
            "start": "2024-04-30 10:40:00.000",
            "end": "2024-04-30 12:10:00.000",
            "type": "lecture",
            "index": 2,
            "color": "blue"
          },
          {
            "id": "3",
            "subject_name": "Английский",
            "start": "2024-05-01 12:40:00.000",
            "end": "2024-05-01 14:10:00.000",
            "type": "seminar",
            "index": 3,
            "color": "sea"
          },
          {
            "id": "4",
            "subject_name": "Матан",
            "homework": "Сделать задания 1-5, принести тетрадь с контрольным расчётом",
            "start": "2024-04-31 14:20:00.000",
            "end": "2024-04-31 15:50:00.000",
            "type": "lecture",
            "index": 4,
            "color": "green"
          },
          {
            "id": "5",
            "subject_name": "Матан",
            "homework": "Сделать задания 1-5, принести тетрадь с контрольным расчётом",
            "start": "2024-04-30 09:30:00.000",
            "end": "2024-04-30 10:30:00.000",
            "type": "seminar",
            "index": 3,
            "color": "yellow"

          },
          {
            "id": "6",
            "subject_name": "Матан",
            "homework": "Сделать задания 1-5, принести тетрадь с контрольным расчётом",
            "start": "2024-04-30 09:30:00.000",
            "end": "2024-04-30 10:30:00.000",
            "type": "seminar",
            "index": 4,
            "color": "yellow"

          },
          {
            "id": "7",
            "subject_name": "Матан",
            "homework": "Сделать задания 1-5, принести тетрадь с контрольным расчётом",
            "start": "2024-05-06 09:30:00.000",
            "end": "2024-05-06 10:30:00.000",
            "type": "seminar",
            "index": 5,
            "color": "yellow"

          },
          {
            "id": "8",
            "subject_name": "Матан",
            "homework": "Сделать задания 1-5, принести тетрадь с контрольным расчётом",
            "start": "2024-05-03 09:30:00.000",
            "end": "2024-05-03 10:30:00.000",
            "type": "seminar",
            "index": 6,
            "color": "yellow"

          }
        ]
      }
    }
  }
]